{"Title": "Curvature Classification", "Abstract": "", "Identifier": "saga:curvatureclassification", "Keywords": [], "Metadata": [], "Input": [{"Title": "DEM", "Abstract": "Elevation", "Identifier": "DEM", "Keywords": [], "Metadata": [], "minOccurs": 1, "maxOccurs": 1, "DataType": "ComplexData", "ComplexData": {"Format": [{"mimeType": "image/bmp", "encoding": "UTF-8", "schema": "", "maximumMegabytes": null, "default": true}, {"mimeType": "image/x-portable-graymap", "encoding": "UTF-8", "schema": "", "maximumMegabytes": null, "default": false}, {"mimeType": "image/tiff", "encoding": "UTF-8", "schema": "", "maximumMegabytes": null, "default": false}, {"mimeType": "image/png", "encoding": "UTF-8", "schema": "", "maximumMegabytes": null, "default": false}, {"mimeType": "application/pdf", "encoding": "UTF-8", "schema": "", "maximumMegabytes": null, "default": false}, {"mimeType": "application/json", "encoding": "UTF-8", "schema": "", "maximumMegabytes": null, "default": false}, {"mimeType": "image/x-portable-pixmap", "encoding": "UTF-8", "schema": "", "maximumMegabytes": null, "default": false}, {"mimeType": "x-world/x-vrt", "encoding": "UTF-8", "schema": "", "maximumMegabytes": null, "default": false}, {"mimeType": "image/x-rgb", "encoding": "UTF-8", "schema": "", "maximumMegabytes": null, "default": false}, {"mimeType": "image/x-portable-anymap", "encoding": "UTF-8", "schema": "", "maximumMegabytes": null, "default": false}, {"mimeType": "image/gif", "encoding": "UTF-8", "schema": "", "maximumMegabytes": null, "default": false}, {"mimeType": "application/pics-rules", "encoding": "UTF-8", "schema": "", "maximumMegabytes": null, "default": false}, {"mimeType": "application/x-netcdf", "encoding": "UTF-8", "schema": "", "maximumMegabytes": null, "default": false}, {"mimeType": "application/octet-stream", "encoding": "UTF-8", "schema": "", "maximumMegabytes": null, "default": false}, {"mimeType": "application/zip", "encoding": "UTF-8", "schema": "", "maximumMegabytes": null, "default": false}, {"mimeType": "image/jpeg", "encoding": "UTF-8", "schema": "", "maximumMegabytes": null, "default": false}, {"mimeType": "text/xml", "encoding": "UTF-8", "schema": "", "maximumMegabytes": null, "default": false}, {"mimeType": "application/x-tar", "encoding": "UTF-8", "schema": "", "maximumMegabytes": null, "default": false}, {"mimeType": "application/x-hdf", "encoding": "UTF-8", "schema": "", "maximumMegabytes": null, "default": false}, {"mimeType": "image/JXL", "encoding": "UTF-8", "schema": "", "maximumMegabytes": null, "default": false}, {"mimeType": "image/x-xpixmap", "encoding": "UTF-8", "schema": "", "maximumMegabytes": null, "default": false}]}}, {"Title": "CLASSES", "Abstract": "Curvature Classification", "Identifier": "CLASSES", "Keywords": [], "Metadata": [], "minOccurs": 1, "maxOccurs": 1, "DataType": "LiteralData", "LiteralData": {"Format": [], "LiteralDataDomain": [{"AllowedValues": [], "DataType": {"reference": "http://www.w3.org/2001/XMLSchema#string", "content": "string"}, "UOM": null, "DefaultValue": "", "default": true}]}}, {"Title": "STRAIGHT", "Abstract": "Threshold Radius", "Identifier": "STRAIGHT", "Keywords": [], "Metadata": [], "minOccurs": 0, "maxOccurs": 1, "DataType": "LiteralData", "LiteralData": {"Format": [], "LiteralDataDomain": [{"AllowedValues": [], "DataType": {"reference": "http://www.w3.org/2001/XMLSchema#string", "content": "string"}, "UOM": null, "DefaultValue": "2000.0", "default": true}]}}, {"Title": "VERTICAL", "Abstract": "Vertical Curvature", "Identifier": "VERTICAL", "Keywords": [], "Metadata": [], "minOccurs": 0, "maxOccurs": 1, "DataType": "LiteralData", "LiteralData": {"Format": [], "LiteralDataDomain": [{"AllowedValues": [{"0": "[0] longitudinal curvature"}, {"1": "[1] profile curvature"}], "DataType": {"reference": "http://www.w3.org/2001/XMLSchema#string", "content": "string"}, "UOM": null, "DefaultValue": "1", "default": true}]}}, {"Title": "HORIZONTAL", "Abstract": "Horizontal Curvature", "Identifier": "HORIZONTAL", "Keywords": [], "Metadata": [], "minOccurs": 0, "maxOccurs": 1, "DataType": "LiteralData", "LiteralData": {"Format": [], "LiteralDataDomain": [{"AllowedValues": [{"0": "[0] cross-sectional curvature"}, {"1": "[1] tangential curvature"}], "DataType": {"reference": "http://www.w3.org/2001/XMLSchema#string", "content": "string"}, "UOM": null, "DefaultValue": "1", "default": true}]}}, {"Title": "SMOOTH", "Abstract": "Smoothing", "Identifier": "SMOOTH", "Keywords": [], "Metadata": [], "minOccurs": 0, "maxOccurs": 1, "DataType": "LiteralData", "LiteralData": {"Format": [], "LiteralDataDomain": [{"AllowedValues": [], "DataType": {"reference": "http://www.w3.org/2001/XMLSchema#string", "content": "string"}, "UOM": null, "DefaultValue": "0.0", "default": true}]}}], "Output": [{"Title": "CLASSES", "Abstract": "Curvature Classification", "Identifier": "CLASSES", "Keywords": [], "Metadata": [], "minOccurs": 1, "maxOccurs": 1, "DataType": "ComplexData", "ComplexData": {"Format": [{"mimeType": "image/tiff", "encoding": "UTF-8", "schema": "", "maximumMegabytes": null, "default": true}]}}]}