{"Title": "Overland Flow Distance to Channel Network", "Abstract": "", "Identifier": "saga:overlandflowdistancetochannelnetwork", "Keywords": [], "Metadata": [], "Input": [{"Title": "ELEVATION", "Abstract": "Elevation", "Identifier": "ELEVATION", "Keywords": [], "Metadata": [], "minOccurs": 1, "maxOccurs": 1, "DataType": "ComplexData", "ComplexData": {"Format": [{"mimeType": "application/pics-rules", "encoding": "UTF-8", "schema": "", "maximumMegabytes": null, "default": true}, {"mimeType": "application/octet-stream", "encoding": "UTF-8", "schema": "", "maximumMegabytes": null, "default": false}, {"mimeType": "image/png", "encoding": "UTF-8", "schema": "", "maximumMegabytes": null, "default": false}, {"mimeType": "x-world/x-vrt", "encoding": "UTF-8", "schema": "", "maximumMegabytes": null, "default": false}, {"mimeType": "image/x-portable-pixmap", "encoding": "UTF-8", "schema": "", "maximumMegabytes": null, "default": false}, {"mimeType": "image/tiff", "encoding": "UTF-8", "schema": "", "maximumMegabytes": null, "default": false}, {"mimeType": "image/x-xpixmap", "encoding": "UTF-8", "schema": "", "maximumMegabytes": null, "default": false}, {"mimeType": "application/x-netcdf", "encoding": "UTF-8", "schema": "", "maximumMegabytes": null, "default": false}, {"mimeType": "application/zip", "encoding": "UTF-8", "schema": "", "maximumMegabytes": null, "default": false}, {"mimeType": "application/pdf", "encoding": "UTF-8", "schema": "", "maximumMegabytes": null, "default": false}, {"mimeType": "text/xml", "encoding": "UTF-8", "schema": "", "maximumMegabytes": null, "default": false}, {"mimeType": "image/bmp", "encoding": "UTF-8", "schema": "", "maximumMegabytes": null, "default": false}, {"mimeType": "image/JXL", "encoding": "UTF-8", "schema": "", "maximumMegabytes": null, "default": false}, {"mimeType": "image/x-rgb", "encoding": "UTF-8", "schema": "", "maximumMegabytes": null, "default": false}, {"mimeType": "application/x-tar", "encoding": "UTF-8", "schema": "", "maximumMegabytes": null, "default": false}, {"mimeType": "image/jpeg", "encoding": "UTF-8", "schema": "", "maximumMegabytes": null, "default": false}, {"mimeType": "image/x-portable-graymap", "encoding": "UTF-8", "schema": "", "maximumMegabytes": null, "default": false}, {"mimeType": "image/gif", "encoding": "UTF-8", "schema": "", "maximumMegabytes": null, "default": false}, {"mimeType": "application/json", "encoding": "UTF-8", "schema": "", "maximumMegabytes": null, "default": false}, {"mimeType": "image/x-portable-anymap", "encoding": "UTF-8", "schema": "", "maximumMegabytes": null, "default": false}, {"mimeType": "application/x-hdf", "encoding": "UTF-8", "schema": "", "maximumMegabytes": null, "default": false}]}}, {"Title": "CHANNELS", "Abstract": "Channel Network", "Identifier": "CHANNELS", "Keywords": [], "Metadata": [], "minOccurs": 1, "maxOccurs": 1, "DataType": "ComplexData", "ComplexData": {"Format": [{"mimeType": "application/pics-rules", "encoding": "UTF-8", "schema": "", "maximumMegabytes": null, "default": true}, {"mimeType": "application/octet-stream", "encoding": "UTF-8", "schema": "", "maximumMegabytes": null, "default": false}, {"mimeType": "image/png", "encoding": "UTF-8", "schema": "", "maximumMegabytes": null, "default": false}, {"mimeType": "x-world/x-vrt", "encoding": "UTF-8", "schema": "", "maximumMegabytes": null, "default": false}, {"mimeType": "image/x-portable-pixmap", "encoding": "UTF-8", "schema": "", "maximumMegabytes": null, "default": false}, {"mimeType": "image/tiff", "encoding": "UTF-8", "schema": "", "maximumMegabytes": null, "default": false}, {"mimeType": "image/x-xpixmap", "encoding": "UTF-8", "schema": "", "maximumMegabytes": null, "default": false}, {"mimeType": "application/x-netcdf", "encoding": "UTF-8", "schema": "", "maximumMegabytes": null, "default": false}, {"mimeType": "application/zip", "encoding": "UTF-8", "schema": "", "maximumMegabytes": null, "default": false}, {"mimeType": "application/pdf", "encoding": "UTF-8", "schema": "", "maximumMegabytes": null, "default": false}, {"mimeType": "text/xml", "encoding": "UTF-8", "schema": "", "maximumMegabytes": null, "default": false}, {"mimeType": "image/bmp", "encoding": "UTF-8", "schema": "", "maximumMegabytes": null, "default": false}, {"mimeType": "image/JXL", "encoding": "UTF-8", "schema": "", "maximumMegabytes": null, "default": false}, {"mimeType": "image/x-rgb", "encoding": "UTF-8", "schema": "", "maximumMegabytes": null, "default": false}, {"mimeType": "application/x-tar", "encoding": "UTF-8", "schema": "", "maximumMegabytes": null, "default": false}, {"mimeType": "image/jpeg", "encoding": "UTF-8", "schema": "", "maximumMegabytes": null, "default": false}, {"mimeType": "image/x-portable-graymap", "encoding": "UTF-8", "schema": "", "maximumMegabytes": null, "default": false}, {"mimeType": "image/gif", "encoding": "UTF-8", "schema": "", "maximumMegabytes": null, "default": false}, {"mimeType": "application/json", "encoding": "UTF-8", "schema": "", "maximumMegabytes": null, "default": false}, {"mimeType": "image/x-portable-anymap", "encoding": "UTF-8", "schema": "", "maximumMegabytes": null, "default": false}, {"mimeType": "application/x-hdf", "encoding": "UTF-8", "schema": "", "maximumMegabytes": null, "default": false}]}}, {"Title": "ROUTE", "Abstract": "Preferred Routing", "Identifier": "ROUTE", "Keywords": [], "Metadata": [], "minOccurs": 0, "maxOccurs": 1, "DataType": "ComplexData", "ComplexData": {"Format": [{"mimeType": "application/pics-rules", "encoding": "UTF-8", "schema": "", "maximumMegabytes": null, "default": true}, {"mimeType": "application/octet-stream", "encoding": "UTF-8", "schema": "", "maximumMegabytes": null, "default": false}, {"mimeType": "image/png", "encoding": "UTF-8", "schema": "", "maximumMegabytes": null, "default": false}, {"mimeType": "x-world/x-vrt", "encoding": "UTF-8", "schema": "", "maximumMegabytes": null, "default": false}, {"mimeType": "image/x-portable-pixmap", "encoding": "UTF-8", "schema": "", "maximumMegabytes": null, "default": false}, {"mimeType": "image/tiff", "encoding": "UTF-8", "schema": "", "maximumMegabytes": null, "default": false}, {"mimeType": "image/x-xpixmap", "encoding": "UTF-8", "schema": "", "maximumMegabytes": null, "default": false}, {"mimeType": "application/x-netcdf", "encoding": "UTF-8", "schema": "", "maximumMegabytes": null, "default": false}, {"mimeType": "application/zip", "encoding": "UTF-8", "schema": "", "maximumMegabytes": null, "default": false}, {"mimeType": "application/pdf", "encoding": "UTF-8", "schema": "", "maximumMegabytes": null, "default": false}, {"mimeType": "text/xml", "encoding": "UTF-8", "schema": "", "maximumMegabytes": null, "default": false}, {"mimeType": "image/bmp", "encoding": "UTF-8", "schema": "", "maximumMegabytes": null, "default": false}, {"mimeType": "image/JXL", "encoding": "UTF-8", "schema": "", "maximumMegabytes": null, "default": false}, {"mimeType": "image/x-rgb", "encoding": "UTF-8", "schema": "", "maximumMegabytes": null, "default": false}, {"mimeType": "application/x-tar", "encoding": "UTF-8", "schema": "", "maximumMegabytes": null, "default": false}, {"mimeType": "image/jpeg", "encoding": "UTF-8", "schema": "", "maximumMegabytes": null, "default": false}, {"mimeType": "image/x-portable-graymap", "encoding": "UTF-8", "schema": "", "maximumMegabytes": null, "default": false}, {"mimeType": "image/gif", "encoding": "UTF-8", "schema": "", "maximumMegabytes": null, "default": false}, {"mimeType": "application/json", "encoding": "UTF-8", "schema": "", "maximumMegabytes": null, "default": false}, {"mimeType": "image/x-portable-anymap", "encoding": "UTF-8", "schema": "", "maximumMegabytes": null, "default": false}, {"mimeType": "application/x-hdf", "encoding": "UTF-8", "schema": "", "maximumMegabytes": null, "default": false}]}}, {"Title": "DISTANCE", "Abstract": "Overland Flow Distance", "Identifier": "DISTANCE", "Keywords": [], "Metadata": [], "minOccurs": 1, "maxOccurs": 1, "DataType": "ComplexData", "ComplexData": {"Format": []}}, {"Title": "DISTVERT", "Abstract": "Vertical Overland Flow Distance", "Identifier": "DISTVERT", "Keywords": [], "Metadata": [], "minOccurs": 1, "maxOccurs": 1, "DataType": "ComplexData", "ComplexData": {"Format": []}}, {"Title": "DISTHORZ", "Abstract": "Horizontal Overland Flow Distance", "Identifier": "DISTHORZ", "Keywords": [], "Metadata": [], "minOccurs": 1, "maxOccurs": 1, "DataType": "ComplexData", "ComplexData": {"Format": []}}, {"Title": "TIME", "Abstract": "Flow Travel Time", "Identifier": "TIME", "Keywords": [], "Metadata": [], "minOccurs": 1, "maxOccurs": 1, "DataType": "ComplexData", "ComplexData": {"Format": []}}, {"Title": "SDR", "Abstract": "Sediment Yield Delivery Ratio", "Identifier": "SDR", "Keywords": [], "Metadata": [], "minOccurs": 1, "maxOccurs": 1, "DataType": "ComplexData", "ComplexData": {"Format": []}}, {"Title": "FIELDS", "Abstract": "Fields", "Identifier": "FIELDS", "Keywords": [], "Metadata": [], "minOccurs": 0, "maxOccurs": 1, "DataType": "ComplexData", "ComplexData": {"Format": [{"mimeType": "application/pics-rules", "encoding": "UTF-8", "schema": "", "maximumMegabytes": null, "default": true}, {"mimeType": "application/octet-stream", "encoding": "UTF-8", "schema": "", "maximumMegabytes": null, "default": false}, {"mimeType": "image/png", "encoding": "UTF-8", "schema": "", "maximumMegabytes": null, "default": false}, {"mimeType": "x-world/x-vrt", "encoding": "UTF-8", "schema": "", "maximumMegabytes": null, "default": false}, {"mimeType": "image/x-portable-pixmap", "encoding": "UTF-8", "schema": "", "maximumMegabytes": null, "default": false}, {"mimeType": "image/tiff", "encoding": "UTF-8", "schema": "", "maximumMegabytes": null, "default": false}, {"mimeType": "image/x-xpixmap", "encoding": "UTF-8", "schema": "", "maximumMegabytes": null, "default": false}, {"mimeType": "application/x-netcdf", "encoding": "UTF-8", "schema": "", "maximumMegabytes": null, "default": false}, {"mimeType": "application/zip", "encoding": "UTF-8", "schema": "", "maximumMegabytes": null, "default": false}, {"mimeType": "application/pdf", "encoding": "UTF-8", "schema": "", "maximumMegabytes": null, "default": false}, {"mimeType": "text/xml", "encoding": "UTF-8", "schema": "", "maximumMegabytes": null, "default": false}, {"mimeType": "image/bmp", "encoding": "UTF-8", "schema": "", "maximumMegabytes": null, "default": false}, {"mimeType": "image/JXL", "encoding": "UTF-8", "schema": "", "maximumMegabytes": null, "default": false}, {"mimeType": "image/x-rgb", "encoding": "UTF-8", "schema": "", "maximumMegabytes": null, "default": false}, {"mimeType": "application/x-tar", "encoding": "UTF-8", "schema": "", "maximumMegabytes": null, "default": false}, {"mimeType": "image/jpeg", "encoding": "UTF-8", "schema": "", "maximumMegabytes": null, "default": false}, {"mimeType": "image/x-portable-graymap", "encoding": "UTF-8", "schema": "", "maximumMegabytes": null, "default": false}, {"mimeType": "image/gif", "encoding": "UTF-8", "schema": "", "maximumMegabytes": null, "default": false}, {"mimeType": "application/json", "encoding": "UTF-8", "schema": "", "maximumMegabytes": null, "default": false}, {"mimeType": "image/x-portable-anymap", "encoding": "UTF-8", "schema": "", "maximumMegabytes": null, "default": false}, {"mimeType": "application/x-hdf", "encoding": "UTF-8", "schema": "", "maximumMegabytes": null, "default": false}]}}, {"Title": "PASSES", "Abstract": "Fields Visited", "Identifier": "PASSES", "Keywords": [], "Metadata": [], "minOccurs": 1, "maxOccurs": 1, "DataType": "ComplexData", "ComplexData": {"Format": []}}, {"Title": "METHOD", "Abstract": "Flow Algorithm", "Identifier": "METHOD", "Keywords": [], "Metadata": [], "minOccurs": 0, "maxOccurs": 1, "DataType": "LiteralData", "LiteralData": {"Format": [], "LiteralDataDomain": [{"AllowedValues": [{"0": "[0] D8"}, {"1": "[1] MFD"}], "DataType": {"reference": "http://www.w3.org/2001/XMLSchema#string", "content": "string"}, "UOM": null, "DefaultValue": "1", "default": true}]}}, {"Title": "BOUNDARY", "Abstract": "Boundary Cells", "Identifier": "BOUNDARY", "Keywords": [], "Metadata": [], "minOccurs": 0, "maxOccurs": 1, "DataType": "LiteralData", "LiteralData": {"Format": [], "LiteralDataDomain": [{"AllowedValues": [], "DataType": {"reference": "http://www.w3.org/2001/XMLSchema#string", "content": "string"}, "UOM": null, "DefaultValue": "False", "default": true}]}}, {"Title": "FLOW_B", "Abstract": "Beta", "Identifier": "FLOW_B", "Keywords": [], "Metadata": [], "minOccurs": 0, "maxOccurs": 1, "DataType": "LiteralData", "LiteralData": {"Format": [], "LiteralDataDomain": [{"AllowedValues": [], "DataType": {"reference": "http://www.w3.org/2001/XMLSchema#string", "content": "string"}, "UOM": null, "DefaultValue": "1.0", "default": true}]}}, {"Title": "FLOW_K", "Abstract": "Manning-Strickler Coefficient", "Identifier": "FLOW_K", "Keywords": [], "Metadata": [], "minOccurs": 0, "maxOccurs": 1, "DataType": "ComplexData", "ComplexData": {"Format": [{"mimeType": "application/pics-rules", "encoding": "UTF-8", "schema": "", "maximumMegabytes": null, "default": true}, {"mimeType": "application/octet-stream", "encoding": "UTF-8", "schema": "", "maximumMegabytes": null, "default": false}, {"mimeType": "image/png", "encoding": "UTF-8", "schema": "", "maximumMegabytes": null, "default": false}, {"mimeType": "x-world/x-vrt", "encoding": "UTF-8", "schema": "", "maximumMegabytes": null, "default": false}, {"mimeType": "image/x-portable-pixmap", "encoding": "UTF-8", "schema": "", "maximumMegabytes": null, "default": false}, {"mimeType": "image/tiff", "encoding": "UTF-8", "schema": "", "maximumMegabytes": null, "default": false}, {"mimeType": "image/x-xpixmap", "encoding": "UTF-8", "schema": "", "maximumMegabytes": null, "default": false}, {"mimeType": "application/x-netcdf", "encoding": "UTF-8", "schema": "", "maximumMegabytes": null, "default": false}, {"mimeType": "application/zip", "encoding": "UTF-8", "schema": "", "maximumMegabytes": null, "default": false}, {"mimeType": "application/pdf", "encoding": "UTF-8", "schema": "", "maximumMegabytes": null, "default": false}, {"mimeType": "text/xml", "encoding": "UTF-8", "schema": "", "maximumMegabytes": null, "default": false}, {"mimeType": "image/bmp", "encoding": "UTF-8", "schema": "", "maximumMegabytes": null, "default": false}, {"mimeType": "image/JXL", "encoding": "UTF-8", "schema": "", "maximumMegabytes": null, "default": false}, {"mimeType": "image/x-rgb", "encoding": "UTF-8", "schema": "", "maximumMegabytes": null, "default": false}, {"mimeType": "application/x-tar", "encoding": "UTF-8", "schema": "", "maximumMegabytes": null, "default": false}, {"mimeType": "image/jpeg", "encoding": "UTF-8", "schema": "", "maximumMegabytes": null, "default": false}, {"mimeType": "image/x-portable-graymap", "encoding": "UTF-8", "schema": "", "maximumMegabytes": null, "default": false}, {"mimeType": "image/gif", "encoding": "UTF-8", "schema": "", "maximumMegabytes": null, "default": false}, {"mimeType": "application/json", "encoding": "UTF-8", "schema": "", "maximumMegabytes": null, "default": false}, {"mimeType": "image/x-portable-anymap", "encoding": "UTF-8", "schema": "", "maximumMegabytes": null, "default": false}, {"mimeType": "application/x-hdf", "encoding": "UTF-8", "schema": "", "maximumMegabytes": null, "default": false}]}}, {"Title": "FLOW_K_DEFAULT", "Abstract": "Default", "Identifier": "FLOW_K_DEFAULT", "Keywords": [], "Metadata": [], "minOccurs": 0, "maxOccurs": 1, "DataType": "LiteralData", "LiteralData": {"Format": [], "LiteralDataDomain": [{"AllowedValues": [], "DataType": {"reference": "http://www.w3.org/2001/XMLSchema#string", "content": "string"}, "UOM": null, "DefaultValue": "20.0", "default": true}]}}, {"Title": "FLOW_R", "Abstract": "Flow Depth", "Identifier": "FLOW_R", "Keywords": [], "Metadata": [], "minOccurs": 0, "maxOccurs": 1, "DataType": "ComplexData", "ComplexData": {"Format": [{"mimeType": "application/pics-rules", "encoding": "UTF-8", "schema": "", "maximumMegabytes": null, "default": true}, {"mimeType": "application/octet-stream", "encoding": "UTF-8", "schema": "", "maximumMegabytes": null, "default": false}, {"mimeType": "image/png", "encoding": "UTF-8", "schema": "", "maximumMegabytes": null, "default": false}, {"mimeType": "x-world/x-vrt", "encoding": "UTF-8", "schema": "", "maximumMegabytes": null, "default": false}, {"mimeType": "image/x-portable-pixmap", "encoding": "UTF-8", "schema": "", "maximumMegabytes": null, "default": false}, {"mimeType": "image/tiff", "encoding": "UTF-8", "schema": "", "maximumMegabytes": null, "default": false}, {"mimeType": "image/x-xpixmap", "encoding": "UTF-8", "schema": "", "maximumMegabytes": null, "default": false}, {"mimeType": "application/x-netcdf", "encoding": "UTF-8", "schema": "", "maximumMegabytes": null, "default": false}, {"mimeType": "application/zip", "encoding": "UTF-8", "schema": "", "maximumMegabytes": null, "default": false}, {"mimeType": "application/pdf", "encoding": "UTF-8", "schema": "", "maximumMegabytes": null, "default": false}, {"mimeType": "text/xml", "encoding": "UTF-8", "schema": "", "maximumMegabytes": null, "default": false}, {"mimeType": "image/bmp", "encoding": "UTF-8", "schema": "", "maximumMegabytes": null, "default": false}, {"mimeType": "image/JXL", "encoding": "UTF-8", "schema": "", "maximumMegabytes": null, "default": false}, {"mimeType": "image/x-rgb", "encoding": "UTF-8", "schema": "", "maximumMegabytes": null, "default": false}, {"mimeType": "application/x-tar", "encoding": "UTF-8", "schema": "", "maximumMegabytes": null, "default": false}, {"mimeType": "image/jpeg", "encoding": "UTF-8", "schema": "", "maximumMegabytes": null, "default": false}, {"mimeType": "image/x-portable-graymap", "encoding": "UTF-8", "schema": "", "maximumMegabytes": null, "default": false}, {"mimeType": "image/gif", "encoding": "UTF-8", "schema": "", "maximumMegabytes": null, "default": false}, {"mimeType": "application/json", "encoding": "UTF-8", "schema": "", "maximumMegabytes": null, "default": false}, {"mimeType": "image/x-portable-anymap", "encoding": "UTF-8", "schema": "", "maximumMegabytes": null, "default": false}, {"mimeType": "application/x-hdf", "encoding": "UTF-8", "schema": "", "maximumMegabytes": null, "default": false}]}}, {"Title": "FLOW_R_DEFAULT", "Abstract": "Default", "Identifier": "FLOW_R_DEFAULT", "Keywords": [], "Metadata": [], "minOccurs": 0, "maxOccurs": 1, "DataType": "LiteralData", "LiteralData": {"Format": [], "LiteralDataDomain": [{"AllowedValues": [], "DataType": {"reference": "http://www.w3.org/2001/XMLSchema#string", "content": "string"}, "UOM": null, "DefaultValue": "0.05", "default": true}]}}], "Output": [{"Title": "DISTANCE", "Abstract": "Overland Flow Distance", "Identifier": "DISTANCE", "Keywords": [], "Metadata": [], "minOccurs": 1, "maxOccurs": 1, "DataType": "ComplexData", "ComplexData": {"Format": [{"mimeType": "image/tiff", "encoding": "UTF-8", "schema": "", "maximumMegabytes": null, "default": true}]}}, {"Title": "DISTVERT", "Abstract": "Vertical Overland Flow Distance", "Identifier": "DISTVERT", "Keywords": [], "Metadata": [], "minOccurs": 1, "maxOccurs": 1, "DataType": "ComplexData", "ComplexData": {"Format": [{"mimeType": "image/tiff", "encoding": "UTF-8", "schema": "", "maximumMegabytes": null, "default": true}]}}, {"Title": "DISTHORZ", "Abstract": "Horizontal Overland Flow Distance", "Identifier": "DISTHORZ", "Keywords": [], "Metadata": [], "minOccurs": 1, "maxOccurs": 1, "DataType": "ComplexData", "ComplexData": {"Format": [{"mimeType": "image/tiff", "encoding": "UTF-8", "schema": "", "maximumMegabytes": null, "default": true}]}}, {"Title": "TIME", "Abstract": "Flow Travel Time", "Identifier": "TIME", "Keywords": [], "Metadata": [], "minOccurs": 1, "maxOccurs": 1, "DataType": "ComplexData", "ComplexData": {"Format": [{"mimeType": "image/tiff", "encoding": "UTF-8", "schema": "", "maximumMegabytes": null, "default": true}]}}, {"Title": "SDR", "Abstract": "Sediment Yield Delivery Ratio", "Identifier": "SDR", "Keywords": [], "Metadata": [], "minOccurs": 1, "maxOccurs": 1, "DataType": "ComplexData", "ComplexData": {"Format": [{"mimeType": "image/tiff", "encoding": "UTF-8", "schema": "", "maximumMegabytes": null, "default": true}]}}, {"Title": "PASSES", "Abstract": "Fields Visited", "Identifier": "PASSES", "Keywords": [], "Metadata": [], "minOccurs": 1, "maxOccurs": 1, "DataType": "ComplexData", "ComplexData": {"Format": [{"mimeType": "image/tiff", "encoding": "UTF-8", "schema": "", "maximumMegabytes": null, "default": true}]}}]}