{"Title": "v.out.pov", "Abstract": "Converts to POV-Ray format, GRASS x,y,z -> POV-Ray x,z,y", "Identifier": "grass7:v.out.pov", "Keywords": [], "Metadata": [], "Input": [{"Title": "input", "Abstract": "Name of input vector map", "Identifier": "input", "Keywords": [], "Metadata": [], "minOccurs": 1, "maxOccurs": 1, "DataType": "ComplexData", "ComplexData": {"Format": [{"mimeType": "text/plain", "encoding": "UTF-8", "schema": "", "maximumMegabytes": null, "default": true}, {"mimeType": "x-world/x-vrt", "encoding": "UTF-8", "schema": "", "maximumMegabytes": null, "default": false}, {"mimeType": "application/json", "encoding": "UTF-8", "schema": "", "maximumMegabytes": null, "default": false}, {"mimeType": "application/vnd.openxmlformats-officedocument.spreadsheetml.sheet", "encoding": "UTF-8", "schema": "", "maximumMegabytes": null, "default": false}, {"mimeType": "application/vnd.oasis.opendocument.spreadsheet", "encoding": "UTF-8", "schema": "", "maximumMegabytes": null, "default": false}, {"mimeType": "application/pdf", "encoding": "UTF-8", "schema": "", "maximumMegabytes": null, "default": false}, {"mimeType": "application/x-netcdf", "encoding": "UTF-8", "schema": "", "maximumMegabytes": null, "default": false}, {"mimeType": "application/zip", "encoding": "UTF-8", "schema": "", "maximumMegabytes": null, "default": false}, {"mimeType": "application/x-tar", "encoding": "UTF-8", "schema": "", "maximumMegabytes": null, "default": false}, {"mimeType": "application/vnd.ms-excel", "encoding": "UTF-8", "schema": "", "maximumMegabytes": null, "default": false}, {"mimeType": "application/x-mif", "encoding": "UTF-8", "schema": "", "maximumMegabytes": null, "default": false}, {"mimeType": "image/svg+xml", "encoding": "UTF-8", "schema": "", "maximumMegabytes": null, "default": false}, {"mimeType": "text/xml", "encoding": "UTF-8", "schema": "", "maximumMegabytes": null, "default": false}]}}, {"Title": "type", "Abstract": "Input feature type", "Identifier": "type", "Keywords": [], "Metadata": [], "minOccurs": 0, "maxOccurs": 1, "DataType": "LiteralData", "LiteralData": {"Format": [], "LiteralDataDomain": [{"AllowedValues": [{"0": "point"}, {"1": "line"}, {"2": "boundary"}, {"3": "centroid"}, {"4": "area"}, {"5": "face"}, {"6": "kernel"}], "DataType": {"reference": "http://www.w3.org/2001/XMLSchema#string", "content": "string"}, "UOM": null, "DefaultValue": "[0, 1, 4, 5]", "default": true}]}}, {"Title": "size", "Abstract": "Radius of sphere for points and tube for lines", "Identifier": "size", "Keywords": [], "Metadata": [], "minOccurs": 0, "maxOccurs": 1, "DataType": "LiteralData", "LiteralData": {"Format": [], "LiteralDataDomain": [{"AllowedValues": [], "DataType": {"reference": "http://www.w3.org/2001/XMLSchema#string", "content": "string"}, "UOM": null, "DefaultValue": "10.0", "default": true}]}}, {"Title": "zmod", "Abstract": "Modifier for z coordinates, this string is appended to each z coordinate", "Identifier": "zmod", "Keywords": [], "Metadata": [], "minOccurs": 0, "maxOccurs": 1, "DataType": "LiteralData", "LiteralData": {"Format": [], "LiteralDataDomain": [{"AllowedValues": [], "DataType": {"reference": "http://www.w3.org/2001/XMLSchema#string", "content": "string"}, "UOM": null, "DefaultValue": "", "default": true}]}}, {"Title": "objmod", "Abstract": "Object modifier (OBJECT_MODIFIER in POV-Ray documentation)", "Identifier": "objmod", "Keywords": [], "Metadata": [], "minOccurs": 0, "maxOccurs": 1, "DataType": "LiteralData", "LiteralData": {"Format": [], "LiteralDataDomain": [{"AllowedValues": [], "DataType": {"reference": "http://www.w3.org/2001/XMLSchema#string", "content": "string"}, "UOM": null, "DefaultValue": "", "default": true}]}}, {"Title": "output", "Abstract": "POV vector", "Identifier": "output", "Keywords": [], "Metadata": [], "minOccurs": 1, "maxOccurs": 1, "DataType": "LiteralData", "LiteralData": {"Format": [], "LiteralDataDomain": [{"AllowedValues": [], "DataType": {"reference": "http://www.w3.org/2001/XMLSchema#string", "content": "string"}, "UOM": null, "DefaultValue": "", "default": true}]}}, {"Title": "GRASS_REGION_PARAMETER", "Abstract": "GRASS GIS 7 region extent", "Identifier": "GRASS_REGION_PARAMETER", "Keywords": [], "Metadata": [], "minOccurs": 0, "maxOccurs": 1, "DataType": "LiteralData", "LiteralData": {"Format": [], "LiteralDataDomain": [{"AllowedValues": [], "DataType": {"reference": "http://www.w3.org/2001/XMLSchema#string", "content": "string"}, "UOM": null, "DefaultValue": "", "default": true}]}}, {"Title": "GRASS_SNAP_TOLERANCE_PARAMETER", "Abstract": "v.in.ogr snap tolerance (-1 = no snap)", "Identifier": "GRASS_SNAP_TOLERANCE_PARAMETER", "Keywords": [], "Metadata": [], "minOccurs": 0, "maxOccurs": 1, "DataType": "LiteralData", "LiteralData": {"Format": [], "LiteralDataDomain": [{"AllowedValues": [], "DataType": {"reference": "http://www.w3.org/2001/XMLSchema#string", "content": "string"}, "UOM": null, "DefaultValue": "-1.0", "default": true}]}}, {"Title": "GRASS_MIN_AREA_PARAMETER", "Abstract": "v.in.ogr min area", "Identifier": "GRASS_MIN_AREA_PARAMETER", "Keywords": [], "Metadata": [], "minOccurs": 0, "maxOccurs": 1, "DataType": "LiteralData", "LiteralData": {"Format": [], "LiteralDataDomain": [{"AllowedValues": [], "DataType": {"reference": "http://www.w3.org/2001/XMLSchema#string", "content": "string"}, "UOM": null, "DefaultValue": "0.0001", "default": true}]}}], "Output": [{"Title": "output", "Abstract": "POV vector", "Identifier": "output", "Keywords": [], "Metadata": [], "minOccurs": 1, "maxOccurs": 1, "DataType": "ComplexData", "ComplexData": {"Format": [{"mimeType": "text/csv", "encoding": "UTF-8", "schema": "", "maximumMegabytes": null, "default": true}, {"mimeType": "text/html", "encoding": "UTF-8", "schema": "", "maximumMegabytes": null, "default": false}]}}]}