{"Title": "Align points to features", "Abstract": "Rotates point features to align them to nearby features.This algorithm calculates the rotation required to align point features with their nearest feature from another reference layer. A new field is added to the output layer which is filled with the angle (in degrees, clockwise) to the nearest reference feature.Optionally, the output layer's symbology can be set to automatically use the calculated rotation field to rotate marker symbols.If desired, a maximum distance to use when aligning points can be set, to avoid aligning isolated points to distant features.", "Identifier": "native:angletonearest", "Keywords": [], "Metadata": [], "Input": [{"Title": "INPUT", "Abstract": "Input layer", "Identifier": "INPUT", "Keywords": [], "Metadata": [], "minOccurs": 1, "maxOccurs": 1, "DataType": "ComplexData", "ComplexData": {"Format": [{"mimeType": "text/plain", "encoding": "UTF-8", "schema": "", "maximumMegabytes": null, "default": true}, {"mimeType": "x-world/x-vrt", "encoding": "UTF-8", "schema": "", "maximumMegabytes": null, "default": false}, {"mimeType": "application/json", "encoding": "UTF-8", "schema": "", "maximumMegabytes": null, "default": false}, {"mimeType": "application/vnd.openxmlformats-officedocument.spreadsheetml.sheet", "encoding": "UTF-8", "schema": "", "maximumMegabytes": null, "default": false}, {"mimeType": "application/vnd.oasis.opendocument.spreadsheet", "encoding": "UTF-8", "schema": "", "maximumMegabytes": null, "default": false}, {"mimeType": "application/pdf", "encoding": "UTF-8", "schema": "", "maximumMegabytes": null, "default": false}, {"mimeType": "application/x-netcdf", "encoding": "UTF-8", "schema": "", "maximumMegabytes": null, "default": false}, {"mimeType": "application/zip", "encoding": "UTF-8", "schema": "", "maximumMegabytes": null, "default": false}, {"mimeType": "application/x-tar", "encoding": "UTF-8", "schema": "", "maximumMegabytes": null, "default": false}, {"mimeType": "application/vnd.ms-excel", "encoding": "UTF-8", "schema": "", "maximumMegabytes": null, "default": false}, {"mimeType": "application/x-mif", "encoding": "UTF-8", "schema": "", "maximumMegabytes": null, "default": false}, {"mimeType": "image/svg+xml", "encoding": "UTF-8", "schema": "", "maximumMegabytes": null, "default": false}, {"mimeType": "text/xml", "encoding": "UTF-8", "schema": "", "maximumMegabytes": null, "default": false}]}}, {"Title": "REFERENCE_LAYER", "Abstract": "Reference layer", "Identifier": "REFERENCE_LAYER", "Keywords": [], "Metadata": [], "minOccurs": 1, "maxOccurs": 1, "DataType": "ComplexData", "ComplexData": {"Format": [{"mimeType": "text/plain", "encoding": "UTF-8", "schema": "", "maximumMegabytes": null, "default": true}, {"mimeType": "x-world/x-vrt", "encoding": "UTF-8", "schema": "", "maximumMegabytes": null, "default": false}, {"mimeType": "application/json", "encoding": "UTF-8", "schema": "", "maximumMegabytes": null, "default": false}, {"mimeType": "application/vnd.openxmlformats-officedocument.spreadsheetml.sheet", "encoding": "UTF-8", "schema": "", "maximumMegabytes": null, "default": false}, {"mimeType": "application/vnd.oasis.opendocument.spreadsheet", "encoding": "UTF-8", "schema": "", "maximumMegabytes": null, "default": false}, {"mimeType": "application/pdf", "encoding": "UTF-8", "schema": "", "maximumMegabytes": null, "default": false}, {"mimeType": "application/x-netcdf", "encoding": "UTF-8", "schema": "", "maximumMegabytes": null, "default": false}, {"mimeType": "application/zip", "encoding": "UTF-8", "schema": "", "maximumMegabytes": null, "default": false}, {"mimeType": "application/x-tar", "encoding": "UTF-8", "schema": "", "maximumMegabytes": null, "default": false}, {"mimeType": "application/vnd.ms-excel", "encoding": "UTF-8", "schema": "", "maximumMegabytes": null, "default": false}, {"mimeType": "application/x-mif", "encoding": "UTF-8", "schema": "", "maximumMegabytes": null, "default": false}, {"mimeType": "image/svg+xml", "encoding": "UTF-8", "schema": "", "maximumMegabytes": null, "default": false}, {"mimeType": "text/xml", "encoding": "UTF-8", "schema": "", "maximumMegabytes": null, "default": false}]}}, {"Title": "MAX_DISTANCE", "Abstract": "Maximum distance to consider", "Identifier": "MAX_DISTANCE", "Keywords": [], "Metadata": [], "minOccurs": 0, "maxOccurs": 1, "DataType": "LiteralData", "LiteralData": {"Format": [], "LiteralDataDomain": [{"AllowedValues": [], "DataType": {"reference": "http://www.w3.org/2001/XMLSchema#string", "content": "string"}, "UOM": null, "DefaultValue": "", "default": true}]}}, {"Title": "FIELD_NAME", "Abstract": "Angle field name", "Identifier": "FIELD_NAME", "Keywords": [], "Metadata": [], "minOccurs": 0, "maxOccurs": 1, "DataType": "LiteralData", "LiteralData": {"Format": [], "LiteralDataDomain": [{"AllowedValues": [], "DataType": {"reference": "http://www.w3.org/2001/XMLSchema#string", "content": "string"}, "UOM": null, "DefaultValue": "rotation", "default": true}]}}, {"Title": "APPLY_SYMBOLOGY", "Abstract": "Automatically apply symbology", "Identifier": "APPLY_SYMBOLOGY", "Keywords": [], "Metadata": [], "minOccurs": 0, "maxOccurs": 1, "DataType": "LiteralData", "LiteralData": {"Format": [], "LiteralDataDomain": [{"AllowedValues": [], "DataType": {"reference": "http://www.w3.org/2001/XMLSchema#string", "content": "string"}, "UOM": null, "DefaultValue": "True", "default": true}]}}, {"Title": "OUTPUT", "Abstract": "Aligned layer", "Identifier": "OUTPUT", "Keywords": [], "Metadata": [], "minOccurs": 0, "maxOccurs": 1, "DataType": "ComplexData", "ComplexData": {"Format": [{"mimeType": "text/plain", "encoding": "UTF-8", "schema": "", "maximumMegabytes": null, "default": true}, {"mimeType": "application/json", "encoding": "UTF-8", "schema": "", "maximumMegabytes": null, "default": false}, {"mimeType": "application/vnd.openxmlformats-officedocument.spreadsheetml.sheet", "encoding": "UTF-8", "schema": "", "maximumMegabytes": null, "default": false}, {"mimeType": "application/vnd.oasis.opendocument.spreadsheet", "encoding": "UTF-8", "schema": "", "maximumMegabytes": null, "default": false}, {"mimeType": "application/vnd.ms-excel", "encoding": "UTF-8", "schema": "", "maximumMegabytes": null, "default": false}, {"mimeType": "text/xml", "encoding": "UTF-8", "schema": "", "maximumMegabytes": null, "default": false}]}}], "Output": [{"Title": "OUTPUT", "Abstract": "Aligned layer", "Identifier": "OUTPUT", "Keywords": [], "Metadata": [], "minOccurs": 1, "maxOccurs": 1, "DataType": "ComplexData", "ComplexData": {"Format": [{"mimeType": "application/zip", "encoding": "UTF-8", "schema": "", "maximumMegabytes": null, "default": true}]}}]}