{"Title": "Features to Raster", "Abstract": "", "Identifier": "saga:featurestoraster", "Keywords": [], "Metadata": [], "Input": [{"Title": "INPUT", "Abstract": "Shapes", "Identifier": "INPUT", "Keywords": [], "Metadata": [], "minOccurs": 1, "maxOccurs": 1, "DataType": "ComplexData", "ComplexData": {"Format": [{"mimeType": "text/plain", "encoding": "UTF-8", "schema": "", "maximumMegabytes": null, "default": true}, {"mimeType": "x-world/x-vrt", "encoding": "UTF-8", "schema": "", "maximumMegabytes": null, "default": false}, {"mimeType": "application/json", "encoding": "UTF-8", "schema": "", "maximumMegabytes": null, "default": false}, {"mimeType": "application/vnd.openxmlformats-officedocument.spreadsheetml.sheet", "encoding": "UTF-8", "schema": "", "maximumMegabytes": null, "default": false}, {"mimeType": "application/vnd.oasis.opendocument.spreadsheet", "encoding": "UTF-8", "schema": "", "maximumMegabytes": null, "default": false}, {"mimeType": "application/pdf", "encoding": "UTF-8", "schema": "", "maximumMegabytes": null, "default": false}, {"mimeType": "application/x-netcdf", "encoding": "UTF-8", "schema": "", "maximumMegabytes": null, "default": false}, {"mimeType": "application/zip", "encoding": "UTF-8", "schema": "", "maximumMegabytes": null, "default": false}, {"mimeType": "application/x-tar", "encoding": "UTF-8", "schema": "", "maximumMegabytes": null, "default": false}, {"mimeType": "application/vnd.ms-excel", "encoding": "UTF-8", "schema": "", "maximumMegabytes": null, "default": false}, {"mimeType": "application/x-mif", "encoding": "UTF-8", "schema": "", "maximumMegabytes": null, "default": false}, {"mimeType": "image/svg+xml", "encoding": "UTF-8", "schema": "", "maximumMegabytes": null, "default": false}, {"mimeType": "text/xml", "encoding": "UTF-8", "schema": "", "maximumMegabytes": null, "default": false}]}}, {"Title": "FIELD", "Abstract": "Attribute", "Identifier": "FIELD", "Keywords": [], "Metadata": [], "minOccurs": 1, "maxOccurs": 1, "DataType": "LiteralData", "LiteralData": {"Format": [], "LiteralDataDomain": [{"AllowedValues": [], "DataType": {"reference": "http://www.w3.org/2001/XMLSchema#string", "content": "string"}, "UOM": null, "DefaultValue": "", "default": true}]}}, {"Title": "OUTPUT", "Abstract": "Output Values", "Identifier": "OUTPUT", "Keywords": [], "Metadata": [], "minOccurs": 0, "maxOccurs": 1, "DataType": "LiteralData", "LiteralData": {"Format": [], "LiteralDataDomain": [{"AllowedValues": [{"0": "[0] data / no-data"}, {"1": "[1] index number"}, {"2": "[2] attribute"}], "DataType": {"reference": "http://www.w3.org/2001/XMLSchema#string", "content": "string"}, "UOM": null, "DefaultValue": "2", "default": true}]}}, {"Title": "MULTIPLE", "Abstract": "Method for Multiple Values", "Identifier": "MULTIPLE", "Keywords": [], "Metadata": [], "minOccurs": 0, "maxOccurs": 1, "DataType": "LiteralData", "LiteralData": {"Format": [], "LiteralDataDomain": [{"AllowedValues": [{"0": "[0] first"}, {"1": "[1] last"}, {"2": "[2] minimum"}, {"3": "[3] maximum"}, {"4": "[4] mean"}], "DataType": {"reference": "http://www.w3.org/2001/XMLSchema#string", "content": "string"}, "UOM": null, "DefaultValue": "1", "default": true}]}}, {"Title": "LINE_TYPE", "Abstract": "Lines", "Identifier": "LINE_TYPE", "Keywords": [], "Metadata": [], "minOccurs": 0, "maxOccurs": 1, "DataType": "LiteralData", "LiteralData": {"Format": [], "LiteralDataDomain": [{"AllowedValues": [{"0": "[0] thin"}, {"1": "[1] thick"}], "DataType": {"reference": "http://www.w3.org/2001/XMLSchema#string", "content": "string"}, "UOM": null, "DefaultValue": "1", "default": true}]}}, {"Title": "POLY_TYPE", "Abstract": "Polygon", "Identifier": "POLY_TYPE", "Keywords": [], "Metadata": [], "minOccurs": 0, "maxOccurs": 1, "DataType": "LiteralData", "LiteralData": {"Format": [], "LiteralDataDomain": [{"AllowedValues": [{"0": "[0] node"}, {"1": "[1] cell"}], "DataType": {"reference": "http://www.w3.org/2001/XMLSchema#string", "content": "string"}, "UOM": null, "DefaultValue": "1", "default": true}]}}, {"Title": "GRID_TYPE", "Abstract": "Data Type", "Identifier": "GRID_TYPE", "Keywords": [], "Metadata": [], "minOccurs": 0, "maxOccurs": 1, "DataType": "LiteralData", "LiteralData": {"Format": [], "LiteralDataDomain": [{"AllowedValues": [{"0": "[0] 1 bit"}, {"1": "[1] 1 byte unsigned integer"}, {"2": "[2] 1 byte signed integer"}, {"3": "[3] 2 byte unsigned integer"}, {"4": "[4] 2 byte signed integer"}, {"5": "[5] 4 byte unsigned integer"}, {"6": "[6] 4 byte signed integer"}, {"7": "[7] 4 byte floating point"}, {"8": "[8] 8 byte floating point"}, {"9": "[9] same as attribute"}], "DataType": {"reference": "http://www.w3.org/2001/XMLSchema#string", "content": "string"}, "UOM": null, "DefaultValue": "9", "default": true}]}}, {"Title": "TARGET_USER_XMIN TARGET_USER_XMAX TARGET_USER_YMIN TARGET_USER_YMAX", "Abstract": "Output extent", "Identifier": "TARGET_USER_XMIN TARGET_USER_XMAX TARGET_USER_YMIN TARGET_USER_YMAX", "Keywords": [], "Metadata": [], "minOccurs": 0, "maxOccurs": 1, "DataType": "LiteralData", "LiteralData": {"Format": [], "LiteralDataDomain": [{"AllowedValues": [], "DataType": {"reference": "http://www.w3.org/2001/XMLSchema#string", "content": "string"}, "UOM": null, "DefaultValue": "", "default": true}]}}, {"Title": "TARGET_USER_SIZE", "Abstract": "Cellsize", "Identifier": "TARGET_USER_SIZE", "Keywords": [], "Metadata": [], "minOccurs": 0, "maxOccurs": 1, "DataType": "LiteralData", "LiteralData": {"Format": [], "LiteralDataDomain": [{"AllowedValues": [], "DataType": {"reference": "http://www.w3.org/2001/XMLSchema#string", "content": "string"}, "UOM": null, "DefaultValue": "100.0", "default": true}]}}, {"Title": "GRID", "Abstract": "Grid", "Identifier": "GRID", "Keywords": [], "Metadata": [], "minOccurs": 1, "maxOccurs": 1, "DataType": "LiteralData", "LiteralData": {"Format": [], "LiteralDataDomain": [{"AllowedValues": [], "DataType": {"reference": "http://www.w3.org/2001/XMLSchema#string", "content": "string"}, "UOM": null, "DefaultValue": "", "default": true}]}}, {"Title": "COUNT", "Abstract": "Number of Values", "Identifier": "COUNT", "Keywords": [], "Metadata": [], "minOccurs": 1, "maxOccurs": 1, "DataType": "LiteralData", "LiteralData": {"Format": [], "LiteralDataDomain": [{"AllowedValues": [], "DataType": {"reference": "http://www.w3.org/2001/XMLSchema#string", "content": "string"}, "UOM": null, "DefaultValue": "", "default": true}]}}], "Output": [{"Title": "GRID", "Abstract": "Grid", "Identifier": "GRID", "Keywords": [], "Metadata": [], "minOccurs": 1, "maxOccurs": 1, "DataType": "ComplexData", "ComplexData": {"Format": [{"mimeType": "image/tiff", "encoding": "UTF-8", "schema": "", "maximumMegabytes": null, "default": true}]}}, {"Title": "COUNT", "Abstract": "Number of Values", "Identifier": "COUNT", "Keywords": [], "Metadata": [], "minOccurs": 1, "maxOccurs": 1, "DataType": "ComplexData", "ComplexData": {"Format": [{"mimeType": "image/tiff", "encoding": "UTF-8", "schema": "", "maximumMegabytes": null, "default": true}]}}]}