{"Title": "Growing Degree Days", "Abstract": "", "Identifier": "saga:growingdegreedays", "Keywords": [], "Metadata": [], "Input": [{"Title": "TMEAN", "Abstract": "Mean Monthly Temperatures", "Identifier": "TMEAN", "Keywords": [], "Metadata": [], "minOccurs": 1, "maxOccurs": 10, "DataType": "ComplexData", "ComplexData": {"Format": [{"mimeType": "image/tiff", "encoding": "UTF-8", "schema": "", "maximumMegabytes": null, "default": true}, {"mimeType": "image/x-rgb", "encoding": "UTF-8", "schema": "", "maximumMegabytes": null, "default": false}, {"mimeType": "image/gif", "encoding": "UTF-8", "schema": "", "maximumMegabytes": null, "default": false}, {"mimeType": "image/jpeg", "encoding": "UTF-8", "schema": "", "maximumMegabytes": null, "default": false}, {"mimeType": "application/json", "encoding": "UTF-8", "schema": "", "maximumMegabytes": null, "default": false}, {"mimeType": "image/bmp", "encoding": "UTF-8", "schema": "", "maximumMegabytes": null, "default": false}, {"mimeType": "image/JXL", "encoding": "UTF-8", "schema": "", "maximumMegabytes": null, "default": false}, {"mimeType": "image/png", "encoding": "UTF-8", "schema": "", "maximumMegabytes": null, "default": false}, {"mimeType": "application/pics-rules", "encoding": "UTF-8", "schema": "", "maximumMegabytes": null, "default": false}, {"mimeType": "x-world/x-vrt", "encoding": "UTF-8", "schema": "", "maximumMegabytes": null, "default": false}, {"mimeType": "application/x-netcdf", "encoding": "UTF-8", "schema": "", "maximumMegabytes": null, "default": false}, {"mimeType": "application/x-hdf", "encoding": "UTF-8", "schema": "", "maximumMegabytes": null, "default": false}, {"mimeType": "image/x-portable-pixmap", "encoding": "UTF-8", "schema": "", "maximumMegabytes": null, "default": false}, {"mimeType": "image/x-portable-anymap", "encoding": "UTF-8", "schema": "", "maximumMegabytes": null, "default": false}, {"mimeType": "image/x-xpixmap", "encoding": "UTF-8", "schema": "", "maximumMegabytes": null, "default": false}, {"mimeType": "application/octet-stream", "encoding": "UTF-8", "schema": "", "maximumMegabytes": null, "default": false}, {"mimeType": "text/xml", "encoding": "UTF-8", "schema": "", "maximumMegabytes": null, "default": false}, {"mimeType": "image/x-portable-graymap", "encoding": "UTF-8", "schema": "", "maximumMegabytes": null, "default": false}, {"mimeType": "application/pdf", "encoding": "UTF-8", "schema": "", "maximumMegabytes": null, "default": false}, {"mimeType": "application/x-tar", "encoding": "UTF-8", "schema": "", "maximumMegabytes": null, "default": false}, {"mimeType": "application/zip", "encoding": "UTF-8", "schema": "", "maximumMegabytes": null, "default": false}]}}, {"Title": "TBASE", "Abstract": "Base Temperature", "Identifier": "TBASE", "Keywords": [], "Metadata": [], "minOccurs": 0, "maxOccurs": 1, "DataType": "LiteralData", "LiteralData": {"Format": [], "LiteralDataDomain": [{"AllowedValues": [], "DataType": {"reference": "http://www.w3.org/2001/XMLSchema#string", "content": "string"}, "UOM": null, "DefaultValue": "10.0", "default": true}]}}, {"Title": "NGDD", "Abstract": "Number of Days above Base Temperature", "Identifier": "NGDD", "Keywords": [], "Metadata": [], "minOccurs": 1, "maxOccurs": 1, "DataType": "LiteralData", "LiteralData": {"Format": [], "LiteralDataDomain": [{"AllowedValues": [], "DataType": {"reference": "http://www.w3.org/2001/XMLSchema#string", "content": "string"}, "UOM": null, "DefaultValue": "", "default": true}]}}, {"Title": "TSUM", "Abstract": "Growing Degree Days", "Identifier": "TSUM", "Keywords": [], "Metadata": [], "minOccurs": 1, "maxOccurs": 1, "DataType": "LiteralData", "LiteralData": {"Format": [], "LiteralDataDomain": [{"AllowedValues": [], "DataType": {"reference": "http://www.w3.org/2001/XMLSchema#string", "content": "string"}, "UOM": null, "DefaultValue": "", "default": true}]}}, {"Title": "FIRST", "Abstract": "First Growing Degree Day", "Identifier": "FIRST", "Keywords": [], "Metadata": [], "minOccurs": 1, "maxOccurs": 1, "DataType": "LiteralData", "LiteralData": {"Format": [], "LiteralDataDomain": [{"AllowedValues": [], "DataType": {"reference": "http://www.w3.org/2001/XMLSchema#string", "content": "string"}, "UOM": null, "DefaultValue": "", "default": true}]}}, {"Title": "LAST", "Abstract": "Last Growing Degree Day", "Identifier": "LAST", "Keywords": [], "Metadata": [], "minOccurs": 1, "maxOccurs": 1, "DataType": "LiteralData", "LiteralData": {"Format": [], "LiteralDataDomain": [{"AllowedValues": [], "DataType": {"reference": "http://www.w3.org/2001/XMLSchema#string", "content": "string"}, "UOM": null, "DefaultValue": "", "default": true}]}}, {"Title": "TARGET", "Abstract": "Degree Sum Target Day", "Identifier": "TARGET", "Keywords": [], "Metadata": [], "minOccurs": 1, "maxOccurs": 1, "DataType": "LiteralData", "LiteralData": {"Format": [], "LiteralDataDomain": [{"AllowedValues": [], "DataType": {"reference": "http://www.w3.org/2001/XMLSchema#string", "content": "string"}, "UOM": null, "DefaultValue": "", "default": true}]}}, {"Title": "TTARGET", "Abstract": "Degree Sum", "Identifier": "TTARGET", "Keywords": [], "Metadata": [], "minOccurs": 0, "maxOccurs": 1, "DataType": "LiteralData", "LiteralData": {"Format": [], "LiteralDataDomain": [{"AllowedValues": [], "DataType": {"reference": "http://www.w3.org/2001/XMLSchema#string", "content": "string"}, "UOM": null, "DefaultValue": "100.0", "default": true}]}}], "Output": [{"Title": "NGDD", "Abstract": "Number of Days above Base Temperature", "Identifier": "NGDD", "Keywords": [], "Metadata": [], "minOccurs": 1, "maxOccurs": 1, "DataType": "ComplexData", "ComplexData": {"Format": [{"mimeType": "image/tiff", "encoding": "UTF-8", "schema": "", "maximumMegabytes": null, "default": true}]}}, {"Title": "TSUM", "Abstract": "Growing Degree Days", "Identifier": "TSUM", "Keywords": [], "Metadata": [], "minOccurs": 1, "maxOccurs": 1, "DataType": "ComplexData", "ComplexData": {"Format": [{"mimeType": "image/tiff", "encoding": "UTF-8", "schema": "", "maximumMegabytes": null, "default": true}]}}, {"Title": "FIRST", "Abstract": "First Growing Degree Day", "Identifier": "FIRST", "Keywords": [], "Metadata": [], "minOccurs": 1, "maxOccurs": 1, "DataType": "ComplexData", "ComplexData": {"Format": [{"mimeType": "image/tiff", "encoding": "UTF-8", "schema": "", "maximumMegabytes": null, "default": true}]}}, {"Title": "LAST", "Abstract": "Last Growing Degree Day", "Identifier": "LAST", "Keywords": [], "Metadata": [], "minOccurs": 1, "maxOccurs": 1, "DataType": "ComplexData", "ComplexData": {"Format": [{"mimeType": "image/tiff", "encoding": "UTF-8", "schema": "", "maximumMegabytes": null, "default": true}]}}, {"Title": "TARGET", "Abstract": "Degree Sum Target Day", "Identifier": "TARGET", "Keywords": [], "Metadata": [], "minOccurs": 1, "maxOccurs": 1, "DataType": "ComplexData", "ComplexData": {"Format": [{"mimeType": "image/tiff", "encoding": "UTF-8", "schema": "", "maximumMegabytes": null, "default": true}]}}]}